call_to_dxcc/__init__.py
call_to_dxcc-0.0.1.dist-info/LICENSE
call_to_dxcc-0.0.1.dist-info/METADATA
call_to_dxcc-0.0.1.dist-info/NOTICE
call_to_dxcc-0.0.1.dist-info/WHEEL
call_to_dxcc-0.0.1.dist-info/top_level.txt
call_to_dxcc-0.0.1.dist-info/RECORD
