Metadata-Version: 2.1
Name: call-to-dxcc
Version: 0.0.1
Summary: Finds DXCC entry for given amateur callsign.
Home-page: https://gitlab.com/andreas_krueger_py/call_to_dxcc
Author: Andreas Krüger (DJ3EI)
Author-email: dj3ei@famsik.de
License: UNKNOWN
Platform: UNKNOWN
Classifier: Programming Language :: Python :: 3
Classifier: Intended Audience :: Developers
Classifier: Operating System :: OS Independent
Classifier: License :: OSI Approved :: Apache Software License
Classifier: Topic :: Communications :: Ham Radio
Requires-Python: >=3.5
